storzandbickel_ble/__init__.py
storzandbickel_ble/client.py
storzandbickel_ble/crafty.py
storzandbickel_ble/device.py
storzandbickel_ble/exceptions.py
storzandbickel_ble/models.py
storzandbickel_ble/protocol.py
storzandbickel_ble/venty.py
storzandbickel_ble/volcano.py
storzandbickel_ble/firmware/__init__.py
storzandbickel_ble/firmware/venty.py
storzandbickel_ble/firmware/volcano.py
storzandbickel_ble-0.1.2.dist-info/METADATA
storzandbickel_ble-0.1.2.dist-info/WHEEL
storzandbickel_ble-0.1.2.dist-info/licenses/LICENSE
storzandbickel_ble-0.1.2.dist-info/RECORD
