Metadata-Version: 2.4
Name: storzandbickel-ble
Version: 0.1.2
Summary: Python library for controlling Storz & Bickel devices via Bluetooth Low Energy (BLE)
Project-URL: Homepage, https://github.com/yourusername/storzandbickel-ble
Project-URL: Documentation, https://storzandbickel-ble.readthedocs.io
Project-URL: Repository, https://github.com/yourusername/storzandbickel-ble
Project-URL: Issues, https://github.com/yourusername/storzandbickel-ble/issues
Author: Storz & Bickel BLE Contributors
License: MIT
License-File: LICENSE
Keywords: bickel,ble,bluetooth,crafty,home-assistant,storz,venty,volcano
Classifier: Development Status :: 3 - Alpha
Classifier: Intended Audience :: Developers
Classifier: License :: OSI Approved :: MIT License
Classifier: Programming Language :: Python :: 3
Classifier: Programming Language :: Python :: 3.11
Classifier: Programming Language :: Python :: 3.12
Classifier: Topic :: Home Automation
Classifier: Topic :: Software Development :: Libraries :: Python Modules
Requires-Python: >=3.11
Requires-Dist: bleak>=0.21.0
Requires-Dist: pydantic>=2.0.0
Provides-Extra: dev
Requires-Dist: bump2version>=1.0.1; extra == 'dev'
Requires-Dist: mypy>=1.7.0; extra == 'dev'
Requires-Dist: pre-commit>=3.5.0; extra == 'dev'
Requires-Dist: pytest-asyncio>=0.21.0; extra == 'dev'
Requires-Dist: pytest-cov>=4.1.0; extra == 'dev'
Requires-Dist: pytest-mock>=3.12.0; extra == 'dev'
Requires-Dist: pytest-timeout>=2.2.0; extra == 'dev'
Requires-Dist: pytest>=8.0.0; extra == 'dev'
Requires-Dist: ruff>=0.1.0; extra == 'dev'
Requires-Dist: sphinx-rtd-theme>=2.0.0; extra == 'dev'
Requires-Dist: sphinx<9.0.0,>=7.0.0; extra == 'dev'
